ocrer/__debug__.py
ocrer/__init__.py
ocrer-2022.3.12.dist-info/LICENSE
ocrer-2022.3.12.dist-info/METADATA
ocrer-2022.3.12.dist-info/WHEEL
ocrer-2022.3.12.dist-info/entry_points.txt
ocrer-2022.3.12.dist-info/top_level.txt
ocrer-2022.3.12.dist-info/RECORD
